filter_url/__init__.py
filter_url/filterurl.py
filter_url/logging_format.py
filter_url-1.2.0.dist-info/licenses/LICENSE
filter_url-1.2.0.dist-info/METADATA
filter_url-1.2.0.dist-info/WHEEL
filter_url-1.2.0.dist-info/top_level.txt
filter_url-1.2.0.dist-info/RECORD
