Metadata-Version: 2.4
Name: filter_url
Version: 1.2.0
Summary: A simple, fast, and configurable URL sensitive data filter
Author-email: Alex Semenyaka <alex.semenyaka@gmail.com>
License: MIT
Project-URL: Homepage, https://github.com/alexsemenyaka/filter_url
Project-URL: Repository, https://github.com/alexsemenyaka/filter_url
Project-URL: Issues, https://github.com/alexsemenyaka/filter_url/issues
Keywords: url,filter,filtering,URL filtering,logging
Classifier: Programming Language :: Python :: 3
Classifier: License :: OSI Approved :: MIT License
Classifier: Operating System :: OS Independent
Classifier: Topic :: System :: Logging
Classifier: Topic :: Text Processing :: Filters
Requires-Python: >=3.10
License-File: LICENSE
Provides-Extra: test
Requires-Dist: pytest; extra == "test"
Requires-Dist: pytest-cov; extra == "test"
Requires-Dist: coveralls; extra == "test"
Dynamic: license-file
